README.md
setup.cfg
setup.py
gormanian/__init__.py
gormanian/calendar.py
gormanian.egg-info/PKG-INFO
gormanian.egg-info/SOURCES.txt
gormanian.egg-info/dependency_links.txt
gormanian.egg-info/top_level.txt