Metadata-Version: 2.1
Name: gormanian
Version: 0.0.7
Summary: A simple library to convert a datetime date to use the superior Gormanian Calendar.
Home-page: https://github.com/Morrolan/gormanian
Author: Ian Havelock
Author-email: ian@morrolan.com
License: MIT
Download-URL: https://github.com/Morrolan/gormanian/archive/v0.0.1.tar.gz
Keywords: Gormanian,Gormanuary,Dave Gorman
Platform: UNKNOWN
Classifier: Development Status :: 3 - Alpha
Classifier: Intended Audience :: Developers
Classifier: Intended Audience :: Education
Classifier: Intended Audience :: Information Technology
Classifier: Topic :: Software Development :: Build Tools
Classifier: Topic :: Software Development :: Libraries :: Python Modules
Classifier: Topic :: Software Development :: Localization
Classifier: License :: OSI Approved :: MIT License
Classifier: Programming Language :: Python :: 3.6
Classifier: Programming Language :: Python :: 3.7
Classifier: Programming Language :: Python :: 3.8
Classifier: Programming Language :: Python :: 3.9
